meraki_dashboard_connect/__init__.py
meraki_dashboard_connect/meraki_connect.py
meraki_dashboard_connect-0.1.2.dist-info/WHEEL
meraki_dashboard_connect-0.1.2.dist-info/METADATA
meraki_dashboard_connect-0.1.2.dist-info/RECORD
