Metadata-Version: 2.1
Name: meraki-dashboard-connect
Version: 0.1.2
Summary: 
Author: Thomas Christory
Requires-Python: >=3.8,<4.0
Classifier: Programming Language :: Python :: 3
Classifier: Programming Language :: Python :: 3.8
Classifier: Programming Language :: Python :: 3.9
Requires-Dist: meraki (>=1.4.3,<2.0.0)
Requires-Dist: meraki-env (>=0.1.1,<0.2.0)
